pnsea/__init__.py
pnsea/constants.py
pnsea/nse.py
pnsea/nsesession.py
pnsea/derivatives/__init__.py
pnsea/derivatives/commodityOptions.py
pnsea/derivatives/equityOptions.py
pnsea/derivatives/indicesOptions.py
pnsea/derivatives/utils.py
pnsea/equity/__init__.py
pnsea/equity/equity.py
pnsea/equity/insider.py
pnsea/mf/__init__.py
pnsea/mf/mf.py
pnsea-1.0.1.dist-info/licenses/LICENSE
pnsea-1.0.1.dist-info/METADATA
pnsea-1.0.1.dist-info/WHEEL
pnsea-1.0.1.dist-info/top_level.txt
pnsea-1.0.1.dist-info/RECORD
