Metadata-Version: 2.4
Name: pnsea
Version: 1.0.1
Summary: A powerful, stealthy unofficial NSE India API wrapper.
Author-email: Anil Sardiwal <theonlyanil@gmail.com>
License: MIT License
Project-URL: Homepage, https://github.com/theonlyanil/pnsea
Project-URL: Bug Tracker, https://github.com/theonlyanil/pnsea/issues
Keywords: nse,india,stock-market,trading,options-chain,finance
Classifier: Programming Language :: Python :: 3
Classifier: License :: OSI Approved :: MIT License
Classifier: Operating System :: OS Independent
Classifier: Topic :: Office/Business :: Financial :: Investment
Requires-Python: >=3.8
License-File: LICENSE
Requires-Dist: stealthkit
Requires-Dist: pandas
Dynamic: license-file
